inck/__init__.py
inck/__main__.py
inck/cli.py
inck/codec.py
inck/exception.py
inck/parser.py
inck-1.0.0.dist-info/LICENSE
inck-1.0.0.dist-info/METADATA
inck-1.0.0.dist-info/WHEEL
inck-1.0.0.dist-info/entry_points.txt
inck-1.0.0.dist-info/top_level.txt
inck-1.0.0.dist-info/RECORD
