Metadata-Version: 2.1
Name: inck
Version: 1.0.0
Summary: Simple spatial domain Steganography, made a CLI tool. Because... Why not?
Home-page: https://github.com/EterDelta/Inck
Author: EterDelta
License: MIT
Classifier: Intended Audience :: End Users/Desktop
Classifier: Intended Audience :: Education
Classifier: Topic :: Scientific/Engineering :: Image Processing
Classifier: License :: OSI Approved :: MIT License
Classifier: Operating System :: OS Independent
Classifier: Programming Language :: Python
Requires-Python: >=3.6
License-File: LICENSE
Requires-Dist: Pillow
